chromades/__init__.py
chromades/cli.py
chromades/colors.py
chromades/progress.py
chromades/spinner.py
chromades/utils.py
chromades-0.1.0.dist-info/licenses/LICENSE
chromades-0.1.0.dist-info/METADATA
chromades-0.1.0.dist-info/WHEEL
chromades-0.1.0.dist-info/entry_points.txt
chromades-0.1.0.dist-info/top_level.txt
chromades-0.1.0.dist-info/RECORD
